<?xml version="1.0" encoding="utf-8"?>
<LanguageData>

  <!-- Mechanicus - Enginseer robe -->

  <OGAM_Apparel_EnginseerRobe.label>引擎先知長袍</OGAM_Apparel_EnginseerRobe.label>
  <OGAM_Apparel_EnginseerRobe.description>引擎先知也許是機械神教最常見的科技神甫。他們自認為是獻身與萬機神的神祕主義工程師, 每個引擎先知都擁有關於如何維護和維修機械和電子技術的豐富知識。與機械神教的大多數神甫不同, 引擎先知幾乎在每一個帝國機構服務（星際戰士除外, 他們的角色由技術軍士負責）, 也經常被分配到帝國衞隊的各個團或泰拉政務院的其他部分。引擎先知是訓練有素的機械神教成員, 致力於維護帝國技術。</OGAM_Apparel_EnginseerRobe.description>

  <!-- Mechanicus - Enginseer Hood -->

  <OGAM_Apparel_EnginseerHood.label>引擎先知兜帽</OGAM_Apparel_EnginseerHood.label>
  <OGAM_Apparel_EnginseerHood.description>引擎先知也許是機械神教最常見的科技神甫。他們自認為是獻身與萬機神的神祕主義工程師, 每個引擎先知都擁有關於如何維護和維修機械和電子技術的豐富知識。與機械神教的大多數神甫不同, 引擎先知幾乎在每一個帝國機構服務（星際戰士除外, 他們的角色由技術軍士負責）, 也經常被分配到帝國衞隊的各個團或泰拉政務院的其他部分。引擎先知是訓練有素的機械神教成員, 致力於維護帝國技術。</OGAM_Apparel_EnginseerHood.description>


  <!-- Mechanicus - Skitarii Legionnaire Armour -->

  <OGAM_Apparel_SkitariiLegionnaireArmour.label>護教軍盔甲</OGAM_Apparel_SkitariiLegionnaireArmour.label>
  <OGAM_Apparel_SkitariiLegionnaireArmour.description>護教軍，又名技術衞隊及護教軍團，是人類帝國機械教的強化人類武裝力量。對常人來説，他們如同天生的戰士。他們以這份神聖的工作為榮，在萬機神指引他們走向榮光時亦榮耀他的偉力。準星與校準儀以不可思議的精度瞄準目標，流電步槍咆哮著發射尋找顱骨的伺服子彈。帶著殉道者力量的鐳武器持續毒化戰場，直到它變得與紅色星球的廢料一般劇毒。裝備著鈦肢體的護教軍徘徊著銀河的各個戰場，在上方看如同火星沙丘中一排排獵殺著的鏽蟻。</OGAM_Apparel_SkitariiLegionnaireArmour.description>


  <!-- Mechanicus - Skitarii Legionnaire Helmet -->

  <OGAM_Apparel_SkitariiLegionnaireHelmet.label>護教軍頭盔</OGAM_Apparel_SkitariiLegionnaireHelmet.label>
  <OGAM_Apparel_SkitariiLegionnaireHelmet.description>護教軍，又名技術衞隊及護教軍團，是人類帝國機械教的強化人類武裝力量。對常人來説，他們如同天生的戰士。他們以這份神聖的工作為榮，在萬機神指引他們走向榮光時亦榮耀他的偉力。準星與校準儀以不可思議的精度瞄準目標，流電步槍咆哮著發射尋找顱骨的伺服子彈。帶著殉道者力量的鐳武器持續毒化戰場，直到它變得與紅色星球的廢料一般劇毒。裝備著鈦肢體的護教軍徘徊著銀河的各個戰場，在上方看如同火星沙丘中一排排獵殺著的鏽蟻。</OGAM_Apparel_SkitariiLegionnaireHelmet.description>


</LanguageData>