<?xml version="1.0" encoding="utf-8" ?>
<Defs>
	<!--==================== Warpfire Damage Type =========================-->
  	<DamageDef ParentName="OG_WarpfireBase">
		<defName>OG_Warpfire</defName>
		<explosionCellMote>Mote_BlastFlame</explosionCellMote>
	</DamageDef>
  
	<!--==================== Warpfire Damage Type =========================-->
  	<DamageDef ParentName="OG_Deamon_WarpfireBase">
		<defName>OG_Chaos_Deamon_Warpfire</defName>
		<explosionCellMote>Mote_BlastFlame</explosionCellMote>
	</DamageDef>
	
	<!--==================== Warpfire Death Damage Type =========================-->
  	<DamageDef ParentName="OG_Deamon_WarpfireDeathBase">
		<defName>OG_Chaos_Deamon_WarpfireDeath</defName>
		<explosionCellMote>Mote_BlastFlame</explosionCellMote>
		<explosionInteriorMote>Mote_ElectricalSpark</explosionInteriorMote>
	</DamageDef>
	
	<!--==================== Warp Storm Strike Damage Type =========================-->
  	<DamageDef ParentName="OG_Deamon_WarpStormStrikeBase">
		<defName>OG_WarpStormStrike</defName>
		<explosionCellMote>Mote_BlastEMP</explosionCellMote>
		<explosionInteriorMote>Mote_ElectricalSpark</explosionInteriorMote>
	</DamageDef>
	
</Defs>