<?xml version="1.0" encoding="utf-8" ?>
<Defs>
  <!-- ========================= Factions ========================= -->
  <!-- Standard -->
	<RulePackDef>
		<defName>OG_Ork_NamerFaction</defName>
		<include>
			<li>OG_Orkoid_NameUtility</li>
		</include>
		<rulePack>
			<rulesStrings>
				<li>name(p=6)->[Kulture] [Klan_B] of [Klan_C]</li>
				<li>name(p=6)->[Kulture] [Klan_B] of [LeaderName]</li>
				<li>name(p=4)->[LeaderName]'z [Klan_B] of [Kulture]</li>
				<li>name(p=2)->[Klan_A] [Klan_B] of [Klan_C]</li>
				
				<!--li>name->[Waaagh] [LeaderName]</li-->
				
				<li>LeaderName(p=4)->[Ork_Warboss]</li>
				<li>LeaderName(p=2)->[Ork_Title_Pre] [Ork_Warboss]</li>
				<li>LeaderName(p=2)->[Ork_Warboss] [Ork_Title_Post]</li>
				<li>LeaderName(p=1)->[Ork_Title_Pre] [Ork_Warboss] [Ork_Title_Post]</li>
				
				<!--
				<li>name-> of da [OGOrkClans1]</li>
				
				<li>name-> of da [OGOrkClans1]</li>
				-->
			</rulesStrings>
		</rulePack>
	</RulePackDef>
	
  <!-- Player -->
	<RulePackDef>
		<defName>OG_Ork_NamerFaction_Player</defName>
		<include>
			<li>OG_Orkoid_NameUtility</li>
		</include>
		<rulePack>
			<rulesStrings>
				<li>name->[Klan_A] [Klan_B] [Klan_C]</li>
				<li>name-> of da [Klan_A]</li>
				<li>name-> of da [Klan_A]</li>
			</rulesStrings>
		</rulePack>
	</RulePackDef>
	
  <!-- Feral -->
	<RulePackDef>
		<defName>OG_Ork_NamerFaction_Feral</defName>
		<include>
			<li>OG_Orkoid_NameUtility</li>
		</include>
		<rulePack>
			<rulesStrings>
				<li>name->[Klan_A] [Klan_B] [Klan_C]</li>
				<li>name-> of da [Klan_A]</li>
				<li>name-> of da [Klan_A]</li>
			</rulesStrings>
		</rulePack>
	</RulePackDef>
	
  <!-- Feral Player -->
	<RulePackDef>
		<defName>OG_Ork_NamerFaction_Feral_Player</defName>
		<include>
			<li>OG_Orkoid_NameUtility</li>
		</include>
		<rulePack>
			<rulesStrings>
				<li>name->[Klan_A] [Klan_B] [Klan_C]</li>
				<li>name-> of da [Klan_A]</li>
				<li>name-> of da [Klan_A]</li>
			</rulesStrings>
		</rulePack>
	</RulePackDef>
	
  <!-- Waaagh -->
	<RulePackDef>
		<defName>OG_Ork_NamerFaction_Waaagh</defName>
		<include>
			<li>OG_Orkoid_NameUtility</li>
		</include>
		<rulePack>
			<rulesStrings>
			<li>name->[Waaagh] [LeaderName]</li>
			<li>Waaagh->Waaagh!</li>
			
			<li>LeaderName->[Ork_Warboss]</li>
			<li>LeaderName->[Ork_Warboss] [Ork_Title_Post]</li>
			<li>LeaderName->[Ork_Title_Pre] [Ork_Warboss]</li>
			<li>LeaderName->[Ork_Title_Pre] [Ork_Warboss] [Ork_Title_Post]</li>
			<!--
			<li>name-> of da [OGOrkClans1]</li>
			
			<li>name-> of da [OGOrkClans1]</li>
			-->
			</rulesStrings>
		</rulePack>
	</RulePackDef>
	
  <!-- Refugee -->
	<RulePackDef>
		<defName>OG_Ork_NamerFaction_Refugee</defName>
		<rulePack>
			<rulesStrings>

				<li>r_name->[adj] [group]</li>

				<li>group->survivaz</li>
				<li>group->gitz</li>
				<li>group->runtz</li>
				<li>group->kastawayz</li>
				<li>group->mob</li>
				<li>group->roamaz</li>
				<li>group->wandaraz</li>
				<li>group->travelaz</li>
				<li>group->nomadaz</li>

				<li>adj->'aggard</li>
				<li>adj->knackered</li>
				<li>adj->abandoned</li>
				<li>adj->exhausted</li>
				<li>adj->lost</li>
				<li>adj->battered</li>
				<li>adj->tough</li>
				<li>adj->dogged</li>
				<li>adj->tenacious</li>

			</rulesStrings>
		</rulePack>
	</RulePackDef>
  
  <!-- ========================= Outposts ========================= -->
	<RulePackDef>
		<defName>OG_Ork_NamerBases</defName>
		<include>
			<li>OG_Orkoid_NameUtility</li>
		</include>
		<rulePack>
			<rulesStrings>
				<li>name->[Ork_Outpost]</li>
			</rulesStrings>
		</rulePack>
	</RulePackDef>

  <!-- ========================= Pawns ========================= -->
  <!-- Ork -->
	<RulePackDef>
		<defName>OG_Ork_NamerPerson</defName>
		<include>
			<li>OG_Orkoid_NameUtility</li>
		</include>
		<rulePack>
			<rulesStrings>
				<li>name->[NameOrk]</li>
			</rulesStrings>
		</rulePack>
	</RulePackDef>
	
  <!-- Grot -->
	<RulePackDef>
		<defName>OG_Grot_NamerPerson</defName>
		<include>
			<li>OG_Orkoid_NameUtility</li>
		</include>
		<rulePack>
			<rulesStrings>
				<li>name->[NameGrot]</li>
			</rulesStrings>
		</rulePack>
	</RulePackDef>

  <!-- Snot -->
	<RulePackDef>
		<defName>OG_Snotling_NamerAnimal</defName>
		<include>
			<li>OG_Orkoid_NameUtility</li>
		</include>
		<rulePack>
			<rulesStrings>
				<li>name->[NameSnot]</li>
			</rulesStrings>
		</rulePack>
	</RulePackDef>
	
  <!-- Squig -->
	<RulePackDef>
		<defName>OG_Squig_NamerAnimal</defName>
		<include>
			<li>OG_Orkoid_NameUtility</li>
		</include>
		<rulePack>
			<rulesStrings>
			<li>name->[NameSquig]</li>
			</rulesStrings>
		</rulePack>
	</RulePackDef>

  <!-- ========================= Orkoid Name Utility ========================= -->
	<RulePackDef>
		<defName>OG_Orkoid_NameUtility</defName>
		<rulePack>
			<rulesStrings>
				<!--li>WordOrk(p=4)->[SylB][SylB]</li>
				<li>WordOrk(p=2)->[SylB][SylB][SylB]</li>
				<li>WordOrk(p=0.2)->[SylB][SylB][SylB][SylB]</li-->
				
				<li>NameOrk(p=8)->[OrkFirst]</li>
				<li>NameOrk(p=4)->[OrkFirst] [OrkSecond]</li>
				<li>NameOrk(p=0.2)->[Ork_First] '[TitlePost]' [Ork_First_B]</li>
				
				<li>OrkFirst(p=4)->[Ork_First_A][Ork_First_B]</li>
				<li>OrkFirst(p=1)->[Ork_First]</li>
				<li>OrkSecond(p=4)->[Ork_Second_A][Ork_Second_B]</li>
				<li>OrkSecond(p=1)->[Ork_Second]</li>
				
				<li>NameGrot(p=15)->[GrotFirst]</li>
				<li>NameGrot(p=10)->[GrotFirst] [GrotSecond]</li>
				<li>NameGrot(p=1)->[GrotFirst] '[Grot_Nick]' [GrotSecond]</li>
				
				<li>GrotFirst(p=4)->[Grot_First_A][Grot_First_B]</li>
				<li>GrotSecond(p=4)->[Grot_Second_A][Grot_Second_B]</li>
				
				<li>NameSquig->[Squig_A][Squig_B]</li>
				
				<li>NameSnot(p=10)->Snot[Ork_First_B]</li>
				<li>NameSnot(p=7)->Snot[Ork_Second_B]</li>
				<li>NameSnot(p=5)->[Ork_First_A]snot</li>
				<li>NameSnot(p=1)->[Ork_Second_A]snot</li>
				
				<li>NameSnot(p=10)->Snot[Grot_First_B]</li>
				<li>NameSnot(p=7)->Snot[Grot_Second_B]</li>
				<li>NameSnot(p=5)->[Grot_First_A]snot</li>
				<li>NameSnot(p=1)->[Grot_Second_A]snot</li>
				
				<li>Klan(p=3)->[Klan_A] [Klan_B]</li>
			</rulesStrings>
			<rulesFiles>
				<li>Klan_A->NameBanks/OG_Ork_Faction_Names_A</li>
				<li>Klan_B->NameBanks/OG_Ork_Faction_Names_B</li>
				<li>Klan_C->NameBanks/OG_Ork_Faction_Names_C</li>
				<li>Kultrue->NameBanks/OG_Ork_Kulture</li>
				
				<li>Ork_Outpost->NameBanks/OG_Ork_BaseNames</li>
				
				<li>Ork_First_A->NameBanks/OG_Ork_Names_First_A</li>
				<li>Ork_First_B->NameBanks/OG_Ork_Names_First_B</li>
				<li>Ork_First->NameBanks/OG_Ork_Names_First</li>
				<li>Ork_Second_A->NameBanks/OG_Ork_Names_Last_A</li>
				<li>Ork_Second_B->NameBanks/OG_Ork_Names_Last_B</li>
				<li>Ork_Second->NameBanks/OG_Ork_Names_Last</li>
				<!--li>Ork_Nick->NameBanks/OG_Ork_Names_Nick</li-->
				
				<li>Ork_Warboss->NameBanks/OG_Ork_Leader_Names</li>
				<li>Ork_Title_Pre->NameBanks/OG_Ork_Leader_Titles_Prefix</li>
				<li>Ork_Title_Post->NameBanks/OG_Ork_Leader_Titles_Postfix</li>
				
				<li>Grot_First_A->NameBanks/OG_Grot_Names_First_A</li>
				<li>Grot_First_B->NameBanks/OG_Grot_Names_First_B</li>
				<li>Grot_Second_A->NameBanks/OG_Grot_Names_Second_A</li>
				<li>Grot_Second_B->NameBanks/OG_Grot_Names_Second_B</li>
				<li>Grot_Nick->NameBanks/OG_Grot_Names_Nick</li>
				
				<li>Squig->NameBanks/OG_Ork_Names_Last</li>
				<li>Squig_A->NameBanks/OG_Squig_Names_A</li>
				<li>Squig_B->NameBanks/OG_Squig_Names_B</li>
			</rulesFiles>
		</rulePack>
	</RulePackDef>

</Defs>